LICENCE
LICENSE
MANIFEST.in
README.md
README.rst
setup.cfg
setup.py
brainutils/__init__.py
brainutils/admin.py
brainutils/ajax.py
brainutils/configuration.py
brainutils/context.py
brainutils/gen_engine.py
brainutils/gen_models.py
brainutils/impexp.py
brainutils/memory.py
brainutils/messages.py
brainutils/mixadmin.py
brainutils/mixforms.py
brainutils/mixins.py
brainutils/models.py
brainutils/properties.py
brainutils/runtests.py
brainutils/signals.py
brainutils/telegrambot.py
brainutils/tests.py
brainutils/urls.py
brainutils/validators.py
brainutils/views.py
brainutils/vmixins.py
brainutils/management/__init__.py
brainutils/management/commands/__init__.py
brainutils/management/commands/codegen.py
brainutils/migrations/0001_initial.py
brainutils/migrations/__init__.py
brainutils/templates/account/Profile.html
brainutils/templates/account/account_inactive.html
brainutils/templates/account/email.html
brainutils/templates/account/email_confirm.html
brainutils/templates/account/login.html
brainutils/templates/account/logout.html
brainutils/templates/account/password_change.html
brainutils/templates/account/password_reset.html
brainutils/templates/account/password_reset_done.html
brainutils/templates/account/password_reset_from_key.html
brainutils/templates/account/password_reset_from_key_done.html
brainutils/templates/account/password_set.html
brainutils/templates/account/signup.html
brainutils/templates/account/signup_closed.html
brainutils/templates/account/verification_sent.html
brainutils/templates/account/verified_email_required.html
brainutils/templates/account/email/email_confirmation_message.html
brainutils/templates/account/email/email_confirmation_signup_message.html
brainutils/templates/account/email/email_confirmation_signup_subject.html
brainutils/templates/account/email/email_confirmation_subject.html
brainutils/templates/account/email/password_reset_key_message.html
brainutils/templates/account/email/password_reset_key_subject.html
django_brain_utils.egg-info/PKG-INFO
django_brain_utils.egg-info/SOURCES.txt
django_brain_utils.egg-info/dependency_links.txt
django_brain_utils.egg-info/top_level.txt